pyvuebot/__init__.py
pyvuebot/cli/__init__.py
"pyvuebot/cli/commands/__init__,py"
pyvuebot/cli/commands/project_commands.py
pyvuebot/cli/commands/version_commands.py
pyvuebot/cli/commands/webhook_commands.py
pyvuebot/cli/main.py
pyvuebot/cli/utils.py
pyvuebot/core/__init__.py
pyvuebot/core/project.py
pyvuebot/core/template.py
pyvuebot/core/webhook.py
pyvuebot/core/wizard.py
pyvuebot/templates/task_manager/.env.example
pyvuebot/templates/task_manager/.gitignore
pyvuebot/templates/task_manager/api/__init__.py
pyvuebot/templates/task_manager/api/db.py
pyvuebot/templates/task_manager/api/index.py
pyvuebot/templates/task_manager/api/models.py
pyvuebot/templates/task_manager/api/routes/__init__.py
pyvuebot/templates/task_manager/api/routes/tasks.py
pyvuebot/templates/task_manager/api/routes/telegram.py
pyvuebot/templates/task_manager/index.html
pyvuebot/templates/task_manager/package.json
pyvuebot/templates/task_manager/public/favicon.ico
pyvuebot/templates/task_manager/requirements.txt
pyvuebot/templates/task_manager/src/App.vue
pyvuebot/templates/task_manager/src/components/TaskForm.vue
pyvuebot/templates/task_manager/src/components/TaskItem.vue
pyvuebot/templates/task_manager/src/components/TaskList.vue
pyvuebot/templates/task_manager/src/components/UserInfo.vue
pyvuebot/templates/task_manager/src/components/base/Dialog.vue
pyvuebot/templates/task_manager/src/main.js
pyvuebot/templates/task_manager/src/services/apiService.js
pyvuebot/templates/task_manager/src/services/telegramService.js
pyvuebot/templates/task_manager/src/store/tasks.js
pyvuebot/templates/task_manager/src/style.css
pyvuebot/templates/task_manager/vercel.json
pyvuebot/templates/task_manager/vite.config.js
pyvuebot-0.2.2.dist-info/METADATA
pyvuebot-0.2.2.dist-info/WHEEL
pyvuebot-0.2.2.dist-info/entry_points.txt
pyvuebot-0.2.2.dist-info/RECORD
