Metadata-Version: 2.3
Name: pyvuebot
Version: 0.2.2
Summary: CLI tool for Telegram Mini Apps
Author: Gemechis Chala
Author-email: venopyx@gmail.com
Requires-Python: >=3.9,<4.0
Classifier: Programming Language :: Python :: 3
Classifier: Programming Language :: Python :: 3.9
Classifier: Programming Language :: Python :: 3.10
Classifier: Programming Language :: Python :: 3.11
Classifier: Programming Language :: Python :: 3.12
Classifier: Programming Language :: Python :: 3.13
Requires-Dist: click (>=8.0.0,<9.0.0)
Requires-Dist: requests (>=2.32.3,<3.0.0)
